{
    "terminal.integrated.shell.linux": "bash",
    "terminal.integrated.shell.osx": "bash",
    "terminal.integrated.shell.windows": "C:\\Windows\\sysnative\\cmd.exe",
    "restructuredtext.confPath": "${workspaceFolder}",
    "files.autoGuessEncoding": false,
    "files.exclude": {
        "**/.git": true,
        "**/.svn": true,
        "**/.hg": true,
        "**/CVS": true,
        "**/.DS_Store": true
    },
    "files.trimTrailingWhitespace": true,
    "files.trimFinalNewlines": true,
    "files.insertFinalNewline": true,
    "files.associations": {
        "wscript": "python",
        "*.h": "c",
        "VERSION": "json"
    },
    "python.linting.enabled": true,
    "python.linting.pylintEnabled": true,
    "pyright.typeCheckingMode": "off",
    "python.formatting.blackPath": "black",
    "python.formatting.provider": "black",
    "python.formatting.blackArgs": [
        "--config=pyproject.toml"
    ],
    "editor.formatOnSave": true,
    "[c]": {
        "editor.formatOnSave": false,
        "files.eol": "\r\n",
    },
    "editor.wordWrap": "off",
    "editor.insertSpaces": true,
    "editor.renderWhitespace": "all",
    "editor.rulers": [
        79
    ],
    "cSpell.languageSettings": [
        {
            "languageId": "*",
            "local": "en",
            "dictionaries": [
                "wordsEn",
                "softwareTerms"
            ]
        },
        {
            "languageId": "python",
            "allowCompoundWords": true,
            "dictionaries": [
                "python",
                "softwareTerms"
            ],
        },
        {
            "languageId": "c,cpp",
            "allowCompoundWords": true,
            "dictionaries": [
                "c",
                "cpp",
                "softwareTerms"
            ],
        },
    ],
    "cSpell.language": "en",
    "cSpell.enabled": true,
    "cSpell.ignorePaths": [
        "build/**",
        ".lock-waf*",
    ],
    "cSpell.ignoreWords": [
        "Qspectre",
        "dylib",
        "iframe",
        "mathjax",
        "SPDX",
        "cygwin",
        "solaris",
        "posix",
        "dlopen",
        "msvc",
        "nologo",
        "Wextra",
        "brtl",
        "bexpall",
        "repo",
        "editorconfig",
        "cmds",
        "readline",
        "rpath",
        "pyproject",
        "bldnode",
        "setenv",
        "shlib",
        "stlib",
        "mkdir",
        "dvidir",
        "psdir",
        "env",
        "pylint",
        "pylintrc",
        "linenos",
        "recurse",
        "sys",
        "shutil",
        "unversioned",
        "waflib",
        "wscript",
        "wscript's",
        "wscripts",
        "Popen",
        "nopyc",
        "nopyo",
        "nopycache",
        "isdir",
        "literalinclude",
        "ltests",
        "cflags",
        "cmcflags",
        "luac",
        "luadll",
        "hdlr",
        "lualib",
        "lapi",
        "lauxlib",
        "lbaselib",
        "lbitlib",
        "lcode",
        "lcorolib",
        "lctype",
        "ldblib",
        "ldebug",
        "ldump",
        "lfunc",
        "lib",
        "linit",
        "liolib",
        "llex",
        "lmathlib",
        "lmem",
        "lobject",
        "lparser",
        "lstate",
        "lstring",
        "lstrlib",
        "ltable",
        "ltablib",
        "ltests",
        "lua",
        "luac",
        "luadll",
        "lundump",
        "lutf",
        "lzio",
        "loadlib",
        "lopcodes",
        "loslib",
        "lprefix",
        "luaconf",
        "maxdepth",
        "nextvar",
        "titlesonly",
        "toctree",
        "tpack",
        "vararg",
        "verybig",
        "LOADK",
        "LOADKX",
        "GETTABUP",
        "SETTABUP",
        "IDIV",
        "BXOR",
        "TFORCALL",
        "TFORLOOP",
        "LUAI",
        "TLIGHTUSERDATA",
        "TNIL",
        "TNONE",
        "TNUMBER",
        "TFUNCTION",
        "LUAL",
        "UACINT",
        "UACNUMBER",
        "TBOOLEAN",
        "TTABLE",
        "GCSTOP",
        "GCRESTART",
        "GCCOLLECT",
        "GCCOUNT",
        "GCSTEP",
        "GCCOUNTB",
        "GCSETPAUSE",
        "GCSETSTEPMUL",
        "GCISRUNNING",
        "NOBINOPR",
        "CIST",
        "TCCL",
        "TLCL",
        "TLCF",
        "TLNGSTR",
        "TSHRSTR",
        "TNUMFLT",
        "ISCOLLECTABLE",
        "TPROTO",
        "TDEADKEY",
        "TUSERDATA",
        "TTHREAD",
        "STRFTIMEC",
        "VCALL",
        "VVARARG",
        "VVOID",
        "VNIL",
        "VTRUE",
        "VFALSE",
        "VKFLT",
        "VKINT",
        "VLOCAL",
        "VUPVAL",
        "VINDEXED",
        "VJMP",
        "VRELOCABLE",
        "SIZET",
        "IGMARK",
        "OFSEP",
        "CLIBS",
        "opnames",
        "opmode",
        "opmodes",
        "nres",
        "Slnt",
        "tname",
        "checknelems",
        "narg",
        "nresults",
        "AppVeyor",
        "confpy",
        "todos",
        "CCDEPS",
        "CPPFLAGS",
        "CPPPATH",
        "LOCALAPPDATA",
        "intelli",
        "sigs",
        "doxygen",
        "Coverity",
        "Webdriver",
        "autocrlf",
        "cygdrive",
        "distclean",
        "ensurepip",
        "gitattributes",
        "gitignore",
        "graphviz",
        "iojs",
        "llvm",
        "mingw",
        "nuget",
        "nunit",
        "popd",
        "pushd",
        "pyyaml",
        "rmfp",
        "startmenu",
        "sysnative",
        "toolchain",
        "userprofile",
        "vcvars",
        "xunit",
        "RUNLEVEL",
        "chsh",
        "devel",
        "freebsd",
        "gnupg",
        "libreadline",
        "pathlib",
        "redhat",
        // Lua op names
        "MOVE",
        "LOADI",
        "LOADF",
        "LOADK",
        "LOADKX",
        "LOADFALSE",
        "LFALSESKIP",
        "LOADTRUE",
        "LOADNIL",
        "GETUPVAL",
        "SETUPVAL",
        "GETTABUP",
        "GETTABLE",
        "GETI",
        "GETFIELD",
        "SETTABUP",
        "SETTABLE",
        "SETI",
        "SETFIELD",
        "NEWTABLE",
        "SELF",
        "ADDI",
        "ADDK",
        "SUBK",
        "MULK",
        "MODK",
        "POWK",
        "DIVK",
        "IDIVK",
        "BANDK",
        "BORK",
        "BXORK",
        "SHRI",
        "SHLI",
        "ADD",
        "SUB",
        "MUL",
        "MOD",
        "POW",
        "DIV",
        "IDIV",
        "BAND",
        "BOR",
        "BXOR",
        "SHL",
        "SHR",
        "MMBIN",
        "MMBINI",
        "MMBINK",
        "UNM",
        "BNOT",
        "NOT",
        "LEN",
        "CONCAT",
        "CLOSE",
        "TBC",
        "JMP",
        "EQ",
        "LT",
        "LE",
        "EQK",
        "EQI",
        "LTI",
        "LEI",
        "GTI",
        "GEI",
        "TEST",
        "TESTSET",
        "CALL",
        "TAILCALL",
        "RETURN",
        "RETURN0",
        "RETURN1",
        "FORLOOP",
        "FORPREP",
        "TFORPREP",
        "TFORCALL",
        "TFORLOOP",
        "SETLIST",
        "CLOSURE",
        "VARARG",
        "VARARGPREP",
        "EXTRAARG"
    ],
    "cSpell.words": []
}
